constellate/__init__.py
constellate/cli/__init__.py
constellate/cli/app.py
constellate/constellate/__init__.py
constellate/constellate/config.py
constellate/constellate/constellation.py
constellate/constellate/star.py
constellate-server/.env.custom.local
constellate-server/.env.production
constellate-server/.gitignore
constellate-server/LICENSE
constellate-server/README.md
constellate-server/next-env.d.ts
constellate-server/next.config.js
constellate-server/package.json
constellate-server/public/constellate_themes/themes.jsx
constellate-server/public/constellations/.gitignore
constellate-server/public/constellations/constellate-tutorial.constellate
constellate-server/public/constellations/gender-in-ai-language-models-what-s-in-a-name.constellate
constellate-server/public/constellations/getting-started.constellate
constellate-server/public/constellations-avail/bayes-in-the-real-world-the-metropolis-hastings-algorithm.constellate
constellate-server/public/constellations-avail/computing-fibonacci-numbers.constellate
constellate-server/public/constellations-avail/constellate-tutorial.constellate
constellate-server/public/constellations-avail/developing-a-collection-of-colors-for-data-visualization.constellate
constellate-server/public/constellations-avail/introduction-to-constellate.constellate
constellate-server/public/constellations-avail/metropolis-hastings-in-the-real-world.constellate
constellate-server/public/constellations-avail/multivariable-calculus-concepts.constellate
constellate-server/public/constellations-avail/testing-jupyter-widgets.constellate
constellate-server/public/images/404_rainy_cloud_dark.png
constellate-server/public/images/404_rainy_cloud_light.png
constellate-server/public/images/favicon/dev/favicon-16x16.png
constellate-server/public/images/favicon/dev/favicon-32x32.png
constellate-server/public/images/favicon/dev/favicon-96x96.png
constellate-server/public/images/favicon/prod/favicon-16x16.png
constellate_app-0.1.9.dist-info/entry_points.txt
constellate_app-0.1.9.dist-info/LICENSE
constellate_app-0.1.9.dist-info/WHEEL
constellate_app-0.1.9.dist-info/METADATA
constellate_app-0.1.9.dist-info/RECORD
