Metadata-Version: 2.1
Name: constellate-app
Version: 0.1.9
Summary: Render Jupyter Notebooks as beautiful interactive webapps
License: MIT
Author: Nicholas Miklaucic
Author-email: nicholas.miklaucic@gmail.com
Requires-Python: >=3.8,<3.11
Classifier: License :: OSI Approved :: MIT License
Classifier: Programming Language :: Python :: 3
Classifier: Programming Language :: Python :: 3.10
Classifier: Programming Language :: Python :: 3.8
Classifier: Programming Language :: Python :: 3.9
Requires-Dist: GitPython (>=3.1.27,<4.0.0)
Requires-Dist: click (>=8.1.3,<9.0.0)
Requires-Dist: click-log (>=0.4.0,<0.5.0)
Requires-Dist: matplotlib (>=3.5.2,<4.0.0)
Requires-Dist: python-slugify (>=6.1.2,<7.0.0)
Requires-Dist: rho-plus (>=0.4.0,<0.5.0)
Requires-Dist: toml (>=0.10.2,<0.11.0)
Requires-Dist: watchdog (>=2.1.9,<3.0.0)
Requires-Dist: yapf (>=0.32.0,<0.33.0)
